plakakia/__init__.py
plakakia/config.yaml
plakakia/make_some_tiles.py
plakakia/make_tiles.py
plakakia/settings.py
plakakia/utils_annotations.py
plakakia/utils_images.py
plakakia/utils_tiling.py
plakakia-0.2.1.dist-info/LICENSE
plakakia-0.2.1.dist-info/METADATA
plakakia-0.2.1.dist-info/WHEEL
plakakia-0.2.1.dist-info/entry_points.txt
plakakia-0.2.1.dist-info/top_level.txt
plakakia-0.2.1.dist-info/RECORD
