Metadata-Version: 2.1
Name: plakakia
Version: 0.2.1
Summary: Python image tiling library for image processing, object detection, etc.
Author: Yannis Kalfas
Author-email: kalfasyan@gmail.com
License-File: LICENSE
Requires-Dist: numpy (>=1.24.2)
Requires-Dist: pandas (>=1.5.3)
Requires-Dist: matplotlib (>=3.7.1)
Requires-Dist: opencv-python (>=4.7.0.72)
Requires-Dist: scipy (>=1.10.1)
Requires-Dist: seaborn (>=0.12.2)
Requires-Dist: lxml (>=4.9.2)
Requires-Dist: imagesize (>=1.4.1)
Requires-Dist: psutil (>=5.9.5)
Requires-Dist: tqdm (>=4.65.0)
Requires-Dist: PyYAML (>=6.0)
Requires-Dist: pyarrow (>=12.0.0)
Requires-Dist: fastparquet (>=2023.4.0)
